muqarnas/__init__.py
muqarnas-0.0.2.dist-info/METADATA
muqarnas-0.0.2.dist-info/WHEEL
muqarnas-0.0.2.dist-info/top_level.txt
muqarnas-0.0.2.dist-info/RECORD
