Metadata-Version: 2.1
Name: muqarnas
Version: 0.0.2
Summary: A Python package for rendering beautiful geometry objects
Author-email: Zhao Liang <mathzhaoliang@gmail.com>
Project-URL: Homepage, https://github.com/neozhaoliang/muqarnas
Classifier: Programming Language :: Python :: 3
Classifier: License :: OSI Approved :: MIT License
Classifier: Operating System :: OS Independent
Requires-Python: >=3.7
